jm_dep2/__init__.py
jm_dep2-0.1.0.dist-info/WHEEL
jm_dep2-0.1.0.dist-info/METADATA
jm_dep2-0.1.0.dist-info/RECORD
