Metadata-Version: 2.1
Name: jm-dep2
Version: 0.1.0
Summary: 
Author: Jean-Mark Wright
Author-email: jeanmark.wright@gmail.com
Requires-Python: >=3.9,<4.0
Classifier: Programming Language :: Python :: 3
Classifier: Programming Language :: Python :: 3.9
Requires-Dist: protobuf (>=3)
